README.md
setup.py
spt_factory/__init__.py
spt_factory/credentials.py
spt_factory/exceptions.py
spt_factory/factory.py
spt_factory/resources.py
spt_factory.egg-info/PKG-INFO
spt_factory.egg-info/SOURCES.txt
spt_factory.egg-info/dependency_links.txt
spt_factory.egg-info/requires.txt
spt_factory.egg-info/top_level.txt
spt_factory/datascience/models/test_model.py
spt_factory/utils/__init__.py
spt_factory/utils/alert_sender.py
spt_factory/utils/grafana_loki.py
spt_factory/utils/prometheus.py
spt_factory/utils/s3_manager.py
test/test.py