Metadata-Version: 2.1
Name: spt-factory
Version: 0.0.25
Summary: SPT resource manager
Author: Mark Poroshin
Author-email: mporoshin@smartpredictiontech.ru
Classifier: Development Status :: 4 - Beta
Classifier: Intended Audience :: Developers
Classifier: Topic :: Software Development :: Build Tools
Classifier: License :: OSI Approved :: MIT License
Classifier: Programming Language :: Python :: 3.7
